[
  {
    "id": "11",
    "title": "wordpress",
    "url": "https://suburbandadmode.com/wp-content/uploads/2018/08/wordpress.jpg",
    "uploadDate": "2018-09-12 06:18:04",
    "mimeType": "image/jpeg",
    "filename": "wordpress.jpg"
  },
  {
    "id": "44",
    "title": "Screenshot 2025-07-30 at 9.06.00 AM",
    "url": "https://suburbandadmode.com/wp-content/uploads/2025/07/Screenshot-2025-07-30-at-9.06.00-AM.png",
    "uploadDate": "2025-07-30 13:06:12",
    "mimeType": "image/png",
    "filename": "Screenshot-2025-07-30-at-9.06.00-AM.png"
  },
  {
    "id": "56",
    "title": "image",
    "url": "https://suburbandadmode.com/wp-content/uploads/2025/07/image.png",
    "uploadDate": "2025-07-30 13:35:14",
    "mimeType": "image/png",
    "filename": "image.png"
  },
  {
    "id": "60",
    "title": "Bhagavans-Bust-with-green-background-812x1024",
    "url": "https://suburbandadmode.com/wp-content/uploads/2025/07/Bhagavans-Bust-with-green-background-812x1024-1.jpg",
    "uploadDate": "2025-07-30 15:00:19",
    "mimeType": "image/jpeg",
    "filename": "Bhagavans-Bust-with-green-background-812x1024-1.jpg"
  },
  {
    "id": "72",
    "title": "IMG_2553",
    "url": "https://suburbandadmode.com/wp-content/uploads/2025/07/IMG_2553-scaled.jpg",
    "uploadDate": "2025-07-30 15:20:25",
    "mimeType": "image/jpeg",
    "filename": "IMG_2553-scaled.jpg"
  },
  {
    "id": "81",
    "title": "img_2505.jpg",
    "url": "https://suburbandadmode.com/wp-content/uploads/2025/07/img_2505.jpg",
    "uploadDate": "2025-07-30 15:53:11",
    "mimeType": "image/jpeg",
    "filename": "img_2505.jpg"
  },
  {
    "id": "82",
    "title": "img_2524.jpg",
    "url": "https://suburbandadmode.com/wp-content/uploads/2025/07/img_2524.jpg",
    "uploadDate": "2025-07-30 15:53:12",
    "mimeType": "image/jpeg",
    "filename": "img_2524.jpg"
  },
  {
    "id": "83",
    "title": "img_2482.jpg",
    "url": "https://suburbandadmode.com/wp-content/uploads/2025/07/img_2482.jpg",
    "uploadDate": "2025-07-30 15:53:13",
    "mimeType": "image/jpeg",
    "filename": "img_2482.jpg"
  },
  {
    "id": "84",
    "title": "img_2552.jpg",
    "url": "https://suburbandadmode.com/wp-content/uploads/2025/07/img_2552.jpg",
    "uploadDate": "2025-07-30 15:53:13",
    "mimeType": "image/jpeg",
    "filename": "img_2552.jpg"
  },
  {
    "id": "85",
    "title": "img_2510.jpg",
    "url": "https://suburbandadmode.com/wp-content/uploads/2025/07/img_2510.jpg",
    "uploadDate": "2025-07-30 15:53:15",
    "mimeType": "image/jpeg",
    "filename": "img_2510.jpg"
  },
  {
    "id": "86",
    "title": "img_2512.jpg",
    "url": "https://suburbandadmode.com/wp-content/uploads/2025/07/img_2512.jpg",
    "uploadDate": "2025-07-30 15:53:16",
    "mimeType": "image/jpeg",
    "filename": "img_2512.jpg"
  },
  {
    "id": "87",
    "title": "img_2511.jpg",
    "url": "https://suburbandadmode.com/wp-content/uploads/2025/07/img_2511.jpg",
    "uploadDate": "2025-07-30 15:53:16",
    "mimeType": "image/jpeg",
    "filename": "img_2511.jpg"
  },
  {
    "id": "88",
    "title": "img_2517.jpg",
    "url": "https://suburbandadmode.com/wp-content/uploads/2025/07/img_2517.jpg",
    "uploadDate": "2025-07-30 15:53:17",
    "mimeType": "image/jpeg",
    "filename": "img_2517.jpg"
  },
  {
    "id": "89",
    "title": "img_2515.jpg",
    "url": "https://suburbandadmode.com/wp-content/uploads/2025/07/img_2515.jpg",
    "uploadDate": "2025-07-30 15:53:17",
    "mimeType": "image/jpeg",
    "filename": "img_2515.jpg"
  },
  {
    "id": "90",
    "title": "img_2492.jpg",
    "url": "https://suburbandadmode.com/wp-content/uploads/2025/07/img_2492.jpg",
    "uploadDate": "2025-07-30 15:53:18",
    "mimeType": "image/jpeg",
    "filename": "img_2492.jpg"
  },
  {
    "id": "91",
    "title": "img_2553.jpg",
    "url": "https://suburbandadmode.com/wp-content/uploads/2025/07/img_2553-1.jpg",
    "uploadDate": "2025-07-30 15:53:19",
    "mimeType": "image/jpeg",
    "filename": "img_2553-1.jpg"
  },
  {
    "id": "92",
    "title": "img_1930.jpg",
    "url": "https://suburbandadmode.com/wp-content/uploads/2025/07/img_1930.jpg",
    "uploadDate": "2025-07-30 15:53:20",
    "mimeType": "image/jpeg",
    "filename": "img_1930.jpg"
  },
  {
    "id": "93",
    "title": "img_2519.jpg",
    "url": "https://suburbandadmode.com/wp-content/uploads/2025/07/img_2519.jpg",
    "uploadDate": "2025-07-30 15:53:21",
    "mimeType": "image/jpeg",
    "filename": "img_2519.jpg"
  },
  {
    "id": "94",
    "title": "img_1943.png",
    "url": "https://suburbandadmode.com/wp-content/uploads/2025/07/img_1943.png",
    "uploadDate": "2025-07-30 15:53:21",
    "mimeType": "image/png",
    "filename": "img_1943.png"
  },
  {
    "id": "95",
    "title": "img_2549.jpg",
    "url": "https://suburbandadmode.com/wp-content/uploads/2025/07/img_2549.jpg",
    "uploadDate": "2025-07-30 15:53:22",
    "mimeType": "image/jpeg",
    "filename": "img_2549.jpg"
  },
  {
    "id": "96",
    "title": "img_2551.jpg",
    "url": "https://suburbandadmode.com/wp-content/uploads/2025/07/img_2551.jpg",
    "uploadDate": "2025-07-30 15:53:22",
    "mimeType": "image/jpeg",
    "filename": "img_2551.jpg"
  },
  {
    "id": "97",
    "title": "img_2550.jpg",
    "url": "https://suburbandadmode.com/wp-content/uploads/2025/07/img_2550.jpg",
    "uploadDate": "2025-07-30 15:53:22",
    "mimeType": "image/jpeg",
    "filename": "img_2550.jpg"
  },
  {
    "id": "98",
    "title": "6ebfa068-4c1f-442d-b8ec-37b051c87d2d.png",
    "url": "https://suburbandadmode.com/wp-content/uploads/2025/07/6ebfa068-4c1f-442d-b8ec-37b051c87d2d.png",
    "uploadDate": "2025-07-30 15:53:23",
    "mimeType": "image/png",
    "filename": "6ebfa068-4c1f-442d-b8ec-37b051c87d2d.png"
  },
  {
    "id": "99",
    "title": "07f12ee6-8aa3-4ade-9bc2-9e0e8965a89f.png",
    "url": "https://suburbandadmode.com/wp-content/uploads/2025/07/07f12ee6-8aa3-4ade-9bc2-9e0e8965a89f.png",
    "uploadDate": "2025-07-30 15:53:24",
    "mimeType": "image/png",
    "filename": "07f12ee6-8aa3-4ade-9bc2-9e0e8965a89f.png"
  },
  {
    "id": "100",
    "title": "img_2509.mp4",
    "url": "https://suburbandadmode.com/wp-content/uploads/2025/07/img_2509.mp4",
    "uploadDate": "2025-07-30 15:53:53",
    "mimeType": "application/octet-stream",
    "filename": "img_2509.mp4"
  },
  {
    "id": "124",
    "title": "android-chrome-512x512",
    "url": "https://suburbandadmode.com/wp-content/uploads/2025/07/android-chrome-512x512-1.png",
    "uploadDate": "2025-07-31 12:18:54",
    "mimeType": "image/png",
    "filename": "android-chrome-512x512-1.png"
  },
  {
    "id": "125",
    "title": "android-chrome-512x512",
    "url": "https://suburbandadmode.com/wp-content/uploads/2025/07/android-chrome-512x512-2.png",
    "uploadDate": "2025-07-31 12:23:08",
    "mimeType": "image/png",
    "filename": "android-chrome-512x512-2.png"
  },
  {
    "id": "156",
    "title": "IMG_2556",
    "url": "https://suburbandadmode.com/wp-content/uploads/2025/08/IMG_2556.jpeg",
    "uploadDate": "2025-08-01 13:24:00",
    "mimeType": "image/jpeg",
    "filename": "IMG_2556.jpeg"
  },
  {
    "id": "158",
    "title": "image",
    "url": "https://suburbandadmode.com/wp-content/uploads/2025/08/image.png",
    "uploadDate": "2025-08-01 14:48:51",
    "mimeType": "image/png",
    "filename": "image.png"
  },
  {
    "id": "160",
    "title": "1",
    "url": "https://suburbandadmode.com/wp-content/uploads/2025/08/1.png",
    "uploadDate": "2025-08-01 15:08:17",
    "mimeType": "image/png",
    "filename": "1.png"
  },
  {
    "id": "162",
    "title": "image(1)",
    "url": "https://suburbandadmode.com/wp-content/uploads/2025/08/image1.png",
    "uploadDate": "2025-08-01 15:09:56",
    "mimeType": "image/png",
    "filename": "image1.png"
  },
  {
    "id": "164",
    "title": "image(2)",
    "url": "https://suburbandadmode.com/wp-content/uploads/2025/08/image2.png",
    "uploadDate": "2025-08-01 15:11:31",
    "mimeType": "image/png",
    "filename": "image2.png"
  },
  {
    "id": "198",
    "title": "Screenshot 2025-08-03 at 4.00.42 PM",
    "url": "https://suburbandadmode.com/wp-content/uploads/2025/08/Screenshot-2025-08-03-at-4.00.42-PM.png",
    "uploadDate": "2025-08-03 20:00:50",
    "mimeType": "image/png",
    "filename": "Screenshot-2025-08-03-at-4.00.42-PM.png"
  },
  {
    "id": "222",
    "title": "AB1913EC-F325-4248-9F25-2CAC5D4309CA",
    "url": "https://suburbandadmode.com/wp-content/uploads/2025/08/AB1913EC-F325-4248-9F25-2CAC5D4309CA.png",
    "uploadDate": "2025-08-07 01:50:27",
    "mimeType": "image/png",
    "filename": "AB1913EC-F325-4248-9F25-2CAC5D4309CA.png"
  },
  {
    "id": "224",
    "title": "04",
    "url": "https://suburbandadmode.com/wp-content/uploads/2025/08/04-scaled.jpeg",
    "uploadDate": "2025-08-07 01:54:47",
    "mimeType": "image/jpeg",
    "filename": "04-scaled.jpeg"
  },
  {
    "id": "226",
    "title": "03",
    "url": "https://suburbandadmode.com/wp-content/uploads/2025/08/03-scaled.jpeg",
    "uploadDate": "2025-08-07 01:56:06",
    "mimeType": "image/jpeg",
    "filename": "03-scaled.jpeg"
  },
  {
    "id": "228",
    "title": "07",
    "url": "https://suburbandadmode.com/wp-content/uploads/2025/08/07-scaled.jpeg",
    "uploadDate": "2025-08-07 01:57:35",
    "mimeType": "image/jpeg",
    "filename": "07-scaled.jpeg"
  },
  {
    "id": "230",
    "title": "06",
    "url": "https://suburbandadmode.com/wp-content/uploads/2025/08/06-scaled.jpeg",
    "uploadDate": "2025-08-07 01:59:28",
    "mimeType": "image/jpeg",
    "filename": "06-scaled.jpeg"
  },
  {
    "id": "234",
    "title": "Art Supplies",
    "url": "https://suburbandadmode.com/wp-content/uploads/2025/08/Art-Supplies-scaled.jpeg",
    "uploadDate": "2025-08-07 02:02:46",
    "mimeType": "image/jpeg",
    "filename": "Art-Supplies-scaled.jpeg"
  },
  {
    "id": "237",
    "title": "letting go",
    "url": "https://suburbandadmode.com/wp-content/uploads/2025/08/letting-go.jpeg",
    "uploadDate": "2025-08-07 02:04:03",
    "mimeType": "image/jpeg",
    "filename": "letting-go.jpeg"
  },
  {
    "id": "239",
    "title": "Cozy Home Interior",
    "url": "https://suburbandadmode.com/wp-content/uploads/2025/08/Cozy-Home-Interior-scaled.jpeg",
    "uploadDate": "2025-08-07 02:05:18",
    "mimeType": "image/jpeg",
    "filename": "Cozy-Home-Interior-scaled.jpeg"
  },
  {
    "id": "242",
    "title": "748EF99F-BCC7-41AB-8435-EE346AF0D442",
    "url": "https://suburbandadmode.com/wp-content/uploads/2025/08/748EF99F-BCC7-41AB-8435-EE346AF0D442.png",
    "uploadDate": "2025-08-07 02:09:22",
    "mimeType": "image/png",
    "filename": "748EF99F-BCC7-41AB-8435-EE346AF0D442.png"
  },
  {
    "id": "246",
    "title": "2DD114B4-31C0-461D-896C-5E644BEA1585",
    "url": "https://suburbandadmode.com/wp-content/uploads/2025/08/2DD114B4-31C0-461D-896C-5E644BEA1585.png",
    "uploadDate": "2025-08-07 02:15:29",
    "mimeType": "image/png",
    "filename": "2DD114B4-31C0-461D-896C-5E644BEA1585.png"
  },
  {
    "id": "250",
    "title": "AB1913EC-F325-4248-9F25-2CAC5D4309CA",
    "url": "https://suburbandadmode.com/wp-content/uploads/2025/08/AB1913EC-F325-4248-9F25-2CAC5D4309CA.jpeg",
    "uploadDate": "2025-08-07 09:24:14",
    "mimeType": "image/jpeg",
    "filename": "AB1913EC-F325-4248-9F25-2CAC5D4309CA.jpeg"
  },
  {
    "id": "253",
    "title": "AB1913EC-F325-4248-9F25-2CAC5D4309CA",
    "url": "https://suburbandadmode.com/wp-content/uploads/2025/08/AB1913EC-F325-4248-9F25-2CAC5D4309CA-1.jpeg",
    "uploadDate": "2025-08-07 09:25:13",
    "mimeType": "image/jpeg",
    "filename": "AB1913EC-F325-4248-9F25-2CAC5D4309CA-1.jpeg"
  },
  {
    "id": "283",
    "title": "IMG_2585",
    "url": "https://suburbandadmode.com/wp-content/uploads/2025/08/IMG_2585-scaled.jpeg",
    "uploadDate": "2025-08-14 11:40:16",
    "mimeType": "image/jpeg",
    "filename": "IMG_2585-scaled.jpeg"
  },
  {
    "id": "356",
    "title": "Cooper",
    "url": "https://suburbandadmode.com/wp-content/uploads/2025/08/cooper_black.woff",
    "uploadDate": "2025-08-20 17:01:42",
    "mimeType": "application/octet-stream",
    "filename": "cooper_black.woff"
  },
  {
    "id": "357",
    "title": "cooper_black",
    "url": "https://suburbandadmode.com/wp-content/uploads/2025/08/cooper_black.woff2",
    "uploadDate": "2025-08-20 17:02:13",
    "mimeType": "application/octet-stream",
    "filename": "cooper_black.woff2"
  },
  {
    "id": "358",
    "title": "cooper_black-italic",
    "url": "https://suburbandadmode.com/wp-content/uploads/2025/08/cooper_black-italic.woff",
    "uploadDate": "2025-08-20 17:02:13",
    "mimeType": "application/octet-stream",
    "filename": "cooper_black-italic.woff"
  },
  {
    "id": "359",
    "title": "cooper_black-italic",
    "url": "https://suburbandadmode.com/wp-content/uploads/2025/08/cooper_black-italic.woff2",
    "uploadDate": "2025-08-20 17:02:13",
    "mimeType": "application/octet-stream",
    "filename": "cooper_black-italic.woff2"
  },
  {
    "id": "360",
    "title": "cooper_bold",
    "url": "https://suburbandadmode.com/wp-content/uploads/2025/08/cooper_bold.woff",
    "uploadDate": "2025-08-20 17:02:13",
    "mimeType": "application/octet-stream",
    "filename": "cooper_bold.woff"
  },
  {
    "id": "361",
    "title": "cooper_bold",
    "url": "https://suburbandadmode.com/wp-content/uploads/2025/08/cooper_bold.woff2",
    "uploadDate": "2025-08-20 17:02:14",
    "mimeType": "application/octet-stream",
    "filename": "cooper_bold.woff2"
  },
  {
    "id": "362",
    "title": "cooper_bold-italic",
    "url": "https://suburbandadmode.com/wp-content/uploads/2025/08/cooper_bold-italic.woff",
    "uploadDate": "2025-08-20 17:02:14",
    "mimeType": "application/octet-stream",
    "filename": "cooper_bold-italic.woff"
  },
  {
    "id": "363",
    "title": "cooper_bold-italic",
    "url": "https://suburbandadmode.com/wp-content/uploads/2025/08/cooper_bold-italic.woff2",
    "uploadDate": "2025-08-20 17:02:14",
    "mimeType": "application/octet-stream",
    "filename": "cooper_bold-italic.woff2"
  },
  {
    "id": "364",
    "title": "cooper_light",
    "url": "https://suburbandadmode.com/wp-content/uploads/2025/08/cooper_light.woff",
    "uploadDate": "2025-08-20 17:02:14",
    "mimeType": "application/octet-stream",
    "filename": "cooper_light.woff"
  },
  {
    "id": "365",
    "title": "cooper_light",
    "url": "https://suburbandadmode.com/wp-content/uploads/2025/08/cooper_light.woff2",
    "uploadDate": "2025-08-20 17:02:14",
    "mimeType": "application/octet-stream",
    "filename": "cooper_light.woff2"
  },
  {
    "id": "366",
    "title": "cooper_light-italic",
    "url": "https://suburbandadmode.com/wp-content/uploads/2025/08/cooper_light-italic.woff",
    "uploadDate": "2025-08-20 17:02:15",
    "mimeType": "application/octet-stream",
    "filename": "cooper_light-italic.woff"
  },
  {
    "id": "367",
    "title": "cooper_light-italic",
    "url": "https://suburbandadmode.com/wp-content/uploads/2025/08/cooper_light-italic.woff2",
    "uploadDate": "2025-08-20 17:02:15",
    "mimeType": "application/octet-stream",
    "filename": "cooper_light-italic.woff2"
  },
  {
    "id": "368",
    "title": "cooper_medium",
    "url": "https://suburbandadmode.com/wp-content/uploads/2025/08/cooper_medium.woff",
    "uploadDate": "2025-08-20 17:02:15",
    "mimeType": "application/octet-stream",
    "filename": "cooper_medium.woff"
  },
  {
    "id": "369",
    "title": "cooper_medium",
    "url": "https://suburbandadmode.com/wp-content/uploads/2025/08/cooper_medium.woff2",
    "uploadDate": "2025-08-20 17:02:15",
    "mimeType": "application/octet-stream",
    "filename": "cooper_medium.woff2"
  },
  {
    "id": "370",
    "title": "cooper_medium-italic",
    "url": "https://suburbandadmode.com/wp-content/uploads/2025/08/cooper_medium-italic.woff",
    "uploadDate": "2025-08-20 17:02:16",
    "mimeType": "application/octet-stream",
    "filename": "cooper_medium-italic.woff"
  },
  {
    "id": "371",
    "title": "cooper_medium-italic",
    "url": "https://suburbandadmode.com/wp-content/uploads/2025/08/cooper_medium-italic.woff2",
    "uploadDate": "2025-08-20 17:02:16",
    "mimeType": "application/octet-stream",
    "filename": "cooper_medium-italic.woff2"
  },
  {
    "id": "373",
    "title": "cooper_black",
    "url": "https://suburbandadmode.com/wp-content/uploads/2025/08/cooper_black-1.woff",
    "uploadDate": "2025-08-20 17:03:46",
    "mimeType": "application/octet-stream",
    "filename": "cooper_black-1.woff"
  },
  {
    "id": "374",
    "title": "cooper_black",
    "url": "https://suburbandadmode.com/wp-content/uploads/2025/08/cooper_black-1.woff2",
    "uploadDate": "2025-08-20 17:03:46",
    "mimeType": "application/octet-stream",
    "filename": "cooper_black-1.woff2"
  },
  {
    "id": "376",
    "title": "cooper_black-italic",
    "url": "https://suburbandadmode.com/wp-content/uploads/2025/08/cooper_black-italic-1.woff",
    "uploadDate": "2025-08-20 17:04:29",
    "mimeType": "application/octet-stream",
    "filename": "cooper_black-italic-1.woff"
  },
  {
    "id": "377",
    "title": "cooper_black-italic",
    "url": "https://suburbandadmode.com/wp-content/uploads/2025/08/cooper_black-italic-1.woff2",
    "uploadDate": "2025-08-20 17:04:29",
    "mimeType": "application/octet-stream",
    "filename": "cooper_black-italic-1.woff2"
  },
  {
    "id": "379",
    "title": "cooper_bold",
    "url": "https://suburbandadmode.com/wp-content/uploads/2025/08/cooper_bold-1.woff",
    "uploadDate": "2025-08-20 17:04:53",
    "mimeType": "application/octet-stream",
    "filename": "cooper_bold-1.woff"
  },
  {
    "id": "380",
    "title": "cooper_bold",
    "url": "https://suburbandadmode.com/wp-content/uploads/2025/08/cooper_bold-1.woff2",
    "uploadDate": "2025-08-20 17:04:54",
    "mimeType": "application/octet-stream",
    "filename": "cooper_bold-1.woff2"
  },
  {
    "id": "382",
    "title": "cooper_bold-italic",
    "url": "https://suburbandadmode.com/wp-content/uploads/2025/08/cooper_bold-italic-1.woff",
    "uploadDate": "2025-08-20 17:05:22",
    "mimeType": "application/octet-stream",
    "filename": "cooper_bold-italic-1.woff"
  },
  {
    "id": "383",
    "title": "cooper_bold-italic",
    "url": "https://suburbandadmode.com/wp-content/uploads/2025/08/cooper_bold-italic-1.woff2",
    "uploadDate": "2025-08-20 17:05:22",
    "mimeType": "application/octet-stream",
    "filename": "cooper_bold-italic-1.woff2"
  },
  {
    "id": "385",
    "title": "cooper_light",
    "url": "https://suburbandadmode.com/wp-content/uploads/2025/08/cooper_light-1.woff",
    "uploadDate": "2025-08-20 17:05:50",
    "mimeType": "application/octet-stream",
    "filename": "cooper_light-1.woff"
  },
  {
    "id": "386",
    "title": "cooper_light",
    "url": "https://suburbandadmode.com/wp-content/uploads/2025/08/cooper_light-1.woff2",
    "uploadDate": "2025-08-20 17:05:50",
    "mimeType": "application/octet-stream",
    "filename": "cooper_light-1.woff2"
  },
  {
    "id": "388",
    "title": "cooper_light-italic",
    "url": "https://suburbandadmode.com/wp-content/uploads/2025/08/cooper_light-italic-1.woff",
    "uploadDate": "2025-08-20 17:06:19",
    "mimeType": "application/octet-stream",
    "filename": "cooper_light-italic-1.woff"
  },
  {
    "id": "389",
    "title": "cooper_light-italic",
    "url": "https://suburbandadmode.com/wp-content/uploads/2025/08/cooper_light-italic-1.woff2",
    "uploadDate": "2025-08-20 17:06:19",
    "mimeType": "application/octet-stream",
    "filename": "cooper_light-italic-1.woff2"
  },
  {
    "id": "391",
    "title": "cooper_medium",
    "url": "https://suburbandadmode.com/wp-content/uploads/2025/08/cooper_medium-1.woff",
    "uploadDate": "2025-08-20 17:06:40",
    "mimeType": "application/octet-stream",
    "filename": "cooper_medium-1.woff"
  },
  {
    "id": "392",
    "title": "cooper_medium",
    "url": "https://suburbandadmode.com/wp-content/uploads/2025/08/cooper_medium-1.woff2",
    "uploadDate": "2025-08-20 17:06:40",
    "mimeType": "application/octet-stream",
    "filename": "cooper_medium-1.woff2"
  },
  {
    "id": "394",
    "title": "cooper_medium-italic",
    "url": "https://suburbandadmode.com/wp-content/uploads/2025/08/cooper_medium-italic-1.woff",
    "uploadDate": "2025-08-20 17:07:03",
    "mimeType": "application/octet-stream",
    "filename": "cooper_medium-italic-1.woff"
  },
  {
    "id": "395",
    "title": "cooper_medium-italic",
    "url": "https://suburbandadmode.com/wp-content/uploads/2025/08/cooper_medium-italic-1.woff2",
    "uploadDate": "2025-08-20 17:07:03",
    "mimeType": "application/octet-stream",
    "filename": "cooper_medium-italic-1.woff2"
  },
  {
    "id": "416",
    "title": "IMG_5489",
    "url": "https://suburbandadmode.com/wp-content/uploads/2025/08/IMG_5489-scaled.jpeg",
    "uploadDate": "2025-08-20 20:40:40",
    "mimeType": "image/jpeg",
    "filename": "IMG_5489-scaled.jpeg"
  },
  {
    "id": "419",
    "title": "FullSizeRender",
    "url": "https://suburbandadmode.com/wp-content/uploads/2025/08/FullSizeRender-scaled.jpeg",
    "uploadDate": "2025-08-20 20:41:44",
    "mimeType": "image/jpeg",
    "filename": "FullSizeRender-scaled.jpeg"
  },
  {
    "id": "422",
    "title": "133398442_t035lzatoz-min",
    "url": "https://suburbandadmode.com/wp-content/uploads/2025/08/133398442_t035lzatoz-min-scaled.jpg",
    "uploadDate": "2025-08-20 21:01:35",
    "mimeType": "image/jpeg",
    "filename": "133398442_t035lzatoz-min-scaled.jpg"
  },
  {
    "id": "423",
    "title": "133398442_45eyckutaz-min",
    "url": "https://suburbandadmode.com/wp-content/uploads/2025/08/133398442_45eyckutaz-min-scaled.jpg",
    "uploadDate": "2025-08-20 21:01:35",
    "mimeType": "image/jpeg",
    "filename": "133398442_45eyckutaz-min-scaled.jpg"
  },
  {
    "id": "424",
    "title": "133398442_ukku9dpp4l-min",
    "url": "https://suburbandadmode.com/wp-content/uploads/2025/08/133398442_ukku9dpp4l-min-scaled.jpg",
    "uploadDate": "2025-08-20 21:01:35",
    "mimeType": "image/jpeg",
    "filename": "133398442_ukku9dpp4l-min-scaled.jpg"
  },
  {
    "id": "425",
    "title": "133398442_zw2ypx3k75-min",
    "url": "https://suburbandadmode.com/wp-content/uploads/2025/08/133398442_zw2ypx3k75-min-scaled.jpg",
    "uploadDate": "2025-08-20 21:01:35",
    "mimeType": "image/jpeg",
    "filename": "133398442_zw2ypx3k75-min-scaled.jpg"
  },
  {
    "id": "426",
    "title": "133398442_y3pva1zxxb-min",
    "url": "https://suburbandadmode.com/wp-content/uploads/2025/08/133398442_y3pva1zxxb-min-scaled.jpg",
    "uploadDate": "2025-08-20 21:01:35",
    "mimeType": "image/jpeg",
    "filename": "133398442_y3pva1zxxb-min-scaled.jpg"
  },
  {
    "id": "447",
    "title": "IMG_0002",
    "url": "https://suburbandadmode.com/wp-content/uploads/2025/08/IMG_0002.jpeg",
    "uploadDate": "2025-08-21 10:45:34",
    "mimeType": "image/jpeg",
    "filename": "IMG_0002.jpeg"
  },
  {
    "id": "525",
    "title": "IMG_2680",
    "url": "https://suburbandadmode.com/wp-content/uploads/2025/08/IMG_2680-scaled.jpeg",
    "uploadDate": "2025-08-28 12:19:54",
    "mimeType": "image/jpeg",
    "filename": "IMG_2680-scaled.jpeg"
  },
  {
    "id": "527",
    "title": "IMG_2684",
    "url": "https://suburbandadmode.com/wp-content/uploads/2025/08/IMG_2684.jpeg",
    "uploadDate": "2025-08-28 15:56:22",
    "mimeType": "image/jpeg",
    "filename": "IMG_2684.jpeg"
  },
  {
    "id": "533",
    "title": "06-1024x683",
    "url": "https://suburbandadmode.com/wp-content/uploads/2025/08/06-1024x683-1.jpeg",
    "uploadDate": "2025-08-29 11:42:34",
    "mimeType": "image/jpeg",
    "filename": "06-1024x683-1.jpeg"
  },
  {
    "id": "544",
    "title": "AB1913EC-F325-4248-9F25-2CAC5D4309CA-1",
    "url": "https://suburbandadmode.com/wp-content/uploads/2025/08/AB1913EC-F325-4248-9F25-2CAC5D4309CA-1-1.jpeg",
    "uploadDate": "2025-08-29 11:45:02",
    "mimeType": "image/jpeg",
    "filename": "AB1913EC-F325-4248-9F25-2CAC5D4309CA-1-1.jpeg"
  },
  {
    "id": "549",
    "title": "IMG_2680-563x1024",
    "url": "https://suburbandadmode.com/wp-content/uploads/2025/08/IMG_2680-563x1024-1.jpeg",
    "uploadDate": "2025-08-29 11:45:48",
    "mimeType": "image/jpeg",
    "filename": "IMG_2680-563x1024-1.jpeg"
  },
  {
    "id": "552",
    "title": "myrtle-burl-writing-desk-tooled-leather",
    "url": "https://suburbandadmode.com/wp-content/uploads/2025/08/myrtle-burl-writing-desk-tooled-leather.webp",
    "uploadDate": "2025-08-29 11:51:05",
    "mimeType": "image/webp",
    "filename": "myrtle-burl-writing-desk-tooled-leather.webp"
  },
  {
    "id": "557",
    "title": "img_2687",
    "url": "https://suburbandadmode.com/wp-content/uploads/2025/08/img_2687.png",
    "uploadDate": "2025-08-29 16:06:53",
    "mimeType": "image/png",
    "filename": "img_2687.png"
  },
  {
    "id": "558",
    "title": "a1f5c10a-e95b-45c9-bf29-d40f97547f19",
    "url": "https://suburbandadmode.com/wp-content/uploads/2025/08/a1f5c10a-e95b-45c9-bf29-d40f97547f19.png",
    "uploadDate": "2025-08-29 16:06:55",
    "mimeType": "image/png",
    "filename": "a1f5c10a-e95b-45c9-bf29-d40f97547f19.png"
  },
  {
    "id": "559",
    "title": "9a0785b7-acf5-495a-aaff-4497221c6bd5",
    "url": "https://suburbandadmode.com/wp-content/uploads/2025/08/9a0785b7-acf5-495a-aaff-4497221c6bd5.png",
    "uploadDate": "2025-08-29 16:06:55",
    "mimeType": "image/png",
    "filename": "9a0785b7-acf5-495a-aaff-4497221c6bd5.png"
  },
  {
    "id": "575",
    "title": "mooji",
    "url": "https://suburbandadmode.com/wp-content/uploads/2025/08/mooji.jpg",
    "uploadDate": "2025-08-30 16:50:33",
    "mimeType": "image/jpeg",
    "filename": "mooji.jpg"
  },
  {
    "id": "577",
    "title": "ramana",
    "url": "https://suburbandadmode.com/wp-content/uploads/2025/08/ramana.jpg",
    "uploadDate": "2025-08-30 16:51:45",
    "mimeType": "image/jpeg",
    "filename": "ramana.jpg"
  },
  {
    "id": "578",
    "title": "Sloww-Ramana-Maharshi-Who-Am-I",
    "url": "https://suburbandadmode.com/wp-content/uploads/2025/08/Sloww-Ramana-Maharshi-Who-Am-I.jpg",
    "uploadDate": "2025-08-30 16:52:14",
    "mimeType": "image/jpeg",
    "filename": "Sloww-Ramana-Maharshi-Who-Am-I.jpg"
  },
  {
    "id": "580",
    "title": "Gemini_Generated_Image_6bc8b6bc8b6bc8b6",
    "url": "https://suburbandadmode.com/wp-content/uploads/2025/08/Gemini_Generated_Image_6bc8b6bc8b6bc8b6.png",
    "uploadDate": "2025-08-30 17:00:38",
    "mimeType": "image/png",
    "filename": "Gemini_Generated_Image_6bc8b6bc8b6bc8b6.png"
  },
  {
    "id": "582",
    "title": "img_2692",
    "url": "https://suburbandadmode.com/wp-content/uploads/2025/08/img_2692.jpg",
    "uploadDate": "2025-08-30 23:24:47",
    "mimeType": "image/jpeg",
    "filename": "img_2692.jpg"
  },
  {
    "id": "599",
    "title": "IMG_2699",
    "url": "https://suburbandadmode.com/wp-content/uploads/2025/08/IMG_2699.jpeg",
    "uploadDate": "2025-08-31 14:21:50",
    "mimeType": "image/jpeg",
    "filename": "IMG_2699.jpeg"
  },
  {
    "id": "601",
    "title": "IMG_2700",
    "url": "https://suburbandadmode.com/wp-content/uploads/2025/08/IMG_2700.png",
    "uploadDate": "2025-08-31 14:26:30",
    "mimeType": "image/png",
    "filename": "IMG_2700.png"
  },
  {
    "id": "604",
    "title": "IMG_2701",
    "url": "https://suburbandadmode.com/wp-content/uploads/2025/08/IMG_2701.png",
    "uploadDate": "2025-08-31 14:32:52",
    "mimeType": "image/png",
    "filename": "IMG_2701.png"
  },
  {
    "id": "609",
    "title": "Quick sheets",
    "url": "https://suburbandadmode.com/wp-content/uploads/2025/09/Quick-sheets.pdf",
    "uploadDate": "2025-09-01 12:13:44",
    "mimeType": "application/octet-stream",
    "filename": "Quick-sheets.pdf"
  },
  {
    "id": "610",
    "title": "IMG_2704",
    "url": "https://suburbandadmode.com/wp-content/uploads/2025/09/IMG_2704.jpeg",
    "uploadDate": "2025-09-01 12:14:55",
    "mimeType": "image/jpeg",
    "filename": "IMG_2704.jpeg"
  },
  {
    "id": "611",
    "title": "IMG_2704",
    "url": "https://suburbandadmode.com/wp-content/uploads/2025/09/IMG_2704-1.jpeg",
    "uploadDate": "2025-09-01 12:15:16",
    "mimeType": "image/jpeg",
    "filename": "IMG_2704-1.jpeg"
  },
  {
    "id": "614",
    "title": "IMG_2709",
    "url": "https://suburbandadmode.com/wp-content/uploads/2025/09/IMG_2709.jpeg",
    "uploadDate": "2025-09-02 22:55:35",
    "mimeType": "image/jpeg",
    "filename": "IMG_2709.jpeg"
  },
  {
    "id": "615",
    "title": "IMG_2709",
    "url": "https://suburbandadmode.com/wp-content/uploads/2025/09/IMG_2709-1.jpeg",
    "uploadDate": "2025-09-02 22:56:38",
    "mimeType": "image/jpeg",
    "filename": "IMG_2709-1.jpeg"
  },
  {
    "id": "622",
    "title": "IMG_2704-1-789x1024",
    "url": "https://suburbandadmode.com/wp-content/uploads/2025/09/IMG_2704-1-789x1024-1.jpeg",
    "uploadDate": "2025-09-03 02:38:53",
    "mimeType": "image/jpeg",
    "filename": "IMG_2704-1-789x1024-1.jpeg"
  },
  {
    "id": "626",
    "title": "1",
    "url": "https://suburbandadmode.com/wp-content/uploads/2025/09/1.png",
    "uploadDate": "2025-09-03 08:14:06",
    "mimeType": "image/png",
    "filename": "1.png"
  },
  {
    "id": "627",
    "title": "2",
    "url": "https://suburbandadmode.com/wp-content/uploads/2025/09/2.png",
    "uploadDate": "2025-09-03 08:14:19",
    "mimeType": "image/png",
    "filename": "2.png"
  },
  {
    "id": "631",
    "title": "IMG_2702",
    "url": "https://suburbandadmode.com/wp-content/uploads/2025/09/IMG_2702.png",
    "uploadDate": "2025-09-07 14:09:21",
    "mimeType": "image/png",
    "filename": "IMG_2702.png"
  }
]